singularity/__init__.py
singularity/cli.py
singularity/client.py
singularity/commands/__init__.py
singularity/commands/cmd_request.py
singularity/commands/cmd_state.py
singularity/commands/cmd_task.py
singularity_cli-0.1.10.dist-info/DESCRIPTION.rst
singularity_cli-0.1.10.dist-info/METADATA
singularity_cli-0.1.10.dist-info/RECORD
singularity_cli-0.1.10.dist-info/WHEEL
singularity_cli-0.1.10.dist-info/entry_points.txt
singularity_cli-0.1.10.dist-info/metadata.json
singularity_cli-0.1.10.dist-info/top_level.txt
