Metadata-Version: 2.0
Name: singularity-cli
Version: 0.1.10
Summary: Opinionated CLI for Singularity PAAS
Home-page: https://github.com/yieldbot/singularity-py
Author: Dave White
Author-email: dwhite@yieldbot.com
License: BSD
Download-URL: https://github.com/yieldbot/singularity-py/tarball/0.1.0
Platform: any
Classifier: Development Status :: 4 - Beta
Classifier: Environment :: Console
Classifier: Intended Audience :: Developers
Classifier: License :: OSI Approved :: MIT License
Classifier: Operating System :: POSIX
Classifier: Operating System :: MacOS :: MacOS X
Classifier: Operating System :: Unix
Classifier: Operating System :: Microsoft :: Windows
Classifier: Programming Language :: Python
Classifier: Programming Language :: Python :: 2
Classifier: Programming Language :: Python :: 3
Classifier: Topic :: Software Development :: Libraries :: Python Modules
Requires-Dist: click
Requires-Dist: requests
Requires-Dist: tabulate
